somni_log/__init__.py
somni_log/constants.py
somni_log/level_filter.py
somni_log/logger.py
unittests/__init__.py
unittests/test_loglevel.py
somni_log-0.1.99.dist-info/LICENSE
somni_log-0.1.99.dist-info/METADATA
somni_log-0.1.99.dist-info/WHEEL
somni_log-0.1.99.dist-info/top_level.txt
somni_log-0.1.99.dist-info/RECORD
