Metadata-Version: 2.1
Name: somni-log
Version: 0.1.99
Summary: A minimal Logger-setup for Python
Home-page: UNKNOWN
Author: Samu Rabin
Author-email: samus_codes@samusoft.net
Maintainer: Samu Rabin
Maintainer-email: samus_codes@samusoft.net
License: MIT
Keywords: logging,logger,minimal
Platform: UNKNOWN
Classifier: Development Status :: 4 - Beta
Classifier: Intended Audience :: Developers
Classifier: Programming Language :: Python :: 3.11
Classifier: Topic :: Software Development :: Libraries :: Python Modules
License-File: LICENSE
